colossal/__init__.py
colossal/colossal.py
libname/__init__.py
libname/colossal.py
Colossalpackage-0.0.3.dist-info/METADATA
Colossalpackage-0.0.3.dist-info/WHEEL
Colossalpackage-0.0.3.dist-info/top_level.txt
Colossalpackage-0.0.3.dist-info/RECORD
