Metadata-Version: 2.1
Name: Colossalpackage
Version: 0.0.3
Summary: Colossal Tech
Author: Maheswara Rao Gunturi
Author-email: <aumnamahsivaya@protonmail.com>
Classifier: Development Status :: 1 - Planning
Classifier: Intended Audience :: Developers
Classifier: Programming Language :: Python :: 3
Classifier: Operating System :: Unix
Classifier: Operating System :: MacOS :: MacOS X
Classifier: Operating System :: Microsoft :: Windows
